ga_data_api/__init__.py
ga_data_api/ga_data_api.py
ga_data_api-0.1.7.dist-info/AUTHORS.rst
ga_data_api-0.1.7.dist-info/LICENSE
ga_data_api-0.1.7.dist-info/METADATA
ga_data_api-0.1.7.dist-info/WHEEL
ga_data_api-0.1.7.dist-info/top_level.txt
ga_data_api-0.1.7.dist-info/RECORD
