Metadata-Version: 2.1
Name: ga-data-api
Version: 0.1.7
Summary: Data API for GA python modules
Home-page: https://github.com/kruegg21/ga_data_api
Author: yes
Author-email: kurtruegg92@gmail.com
License: MIT license
Keywords: ga_data_api
Platform: UNKNOWN
Classifier: Development Status :: 2 - Pre-Alpha
Classifier: Intended Audience :: Developers
Classifier: License :: OSI Approved :: MIT License
Classifier: Natural Language :: English
Classifier: Programming Language :: Python :: 2
Classifier: Programming Language :: Python :: 2.7
Classifier: Programming Language :: Python :: 3
Classifier: Programming Language :: Python :: 3.4
Classifier: Programming Language :: Python :: 3.5
Classifier: Programming Language :: Python :: 3.6
Classifier: Programming Language :: Python :: 3.7
